<annotation>
	<folder></folder>
	<filename>150_jpg.rf.925f7aad52cbead0fd098e39be9e7e0c.jpg</filename>
	<path>150_jpg.rf.925f7aad52cbead0fd098e39be9e7e0c.jpg</path>
	<source>
		<database>roboflow.com</database>
	</source>
	<size>
		<width>300</width>
		<height>168</height>
		<depth>3</depth>
	</size>
	<segmented>0</segmented>
	<object>
		<name>Ship</name>
		<pose>Unspecified</pose>
		<truncated>0</truncated>
		<difficult>0</difficult>
		<occluded>0</occluded>
		<bndbox>
			<xmin>74</xmin>
			<xmax>223</xmax>
			<ymin>68</ymin>
			<ymax>135</ymax>
		</bndbox>
		<polygon>
			<x1>222.070312</x1>
			<y1>110.449219</y1>
			<x2>199.511719</x2>
			<y2>102.539062</y2>
			<x3>194.824219</x3>
			<y3>88.476562</y3>
			<x4>192.480469</x4>
			<y4>101.367188</y4>
			<x5>176.660156</x5>
			<y5>100.195312</y5>
			<x6>173.730469</x6>
			<y6>72.65625</y6>
			<x7>170.507812</x7>
			<y7>84.667969</y7>
			<x8>165.527344</x8>
			<y8>85.546875</y8>
			<x9>157.03125</x9>
			<y9>78.808594</y9>
			<x10>156.152344</x10>
			<y10>73.242188</y10>
			<x11>146.191406</x11>
			<y11>77.34375</y11>
			<x12>142.089844</x12>
			<y12>68.554688</y12>
			<x13>141.796875</x13>
			<y13>78.222656</y13>
			<x14>137.402344</x14>
			<y14>82.617188</y14>
			<x15>135.644531</x15>
			<y15>67.382812</y15>
			<x16>134.765625</x16>
			<y16>84.667969</y16>
			<x17>128.027344</x17>
			<y17>99.609375</y17>
			<x18>120.410156</x18>
			<y18>100.78125</y18>
			<x19>114.84375</x19>
			<y19>90.527344</y19>
			<x20>106.933594</x20>
			<y20>89.0625</y20>
			<x21>102.246094</x21>
			<y21>80.859375</y21>
			<x22>98.4375</x22>
			<y22>84.082031</y22>
			<x23>98.4375</x23>
			<y23>95.214844</y23>
			<x24>106.347656</x24>
			<y24>96.679688</y24>
			<x25>106.640625</x25>
			<y25>102.832031</y25>
			<x26>99.902344</x26>
			<y26>101.953125</y26>
			<x27>96.386719</x27>
			<y27>105.46875</y27>
			<x28>82.324219</x28>
			<y28>101.953125</y28>
			<x29>73.242188</x29>
			<y29>110.449219</y29>
			<x30>73.828125</x30>
			<y30>126.269531</y30>
			<x31>78.808594</x31>
			<y31>131.25</y31>
			<x32>198.046875</x32>
			<y32>134.472656</y32>
			<x33>212.988281</x33>
			<y33>134.179688</y33>
			<x34>222.070312</x34>
			<y34>110.449219</y34>
		</polygon>
	</object>
</annotation>
