<annotation>
	<folder></folder>
	<filename>2804216_jpg.rf.44daf191d84bbff37df4be3320d050e5.jpg</filename>
	<path>2804216_jpg.rf.44daf191d84bbff37df4be3320d050e5.jpg</path>
	<source>
		<database>roboflow.com</database>
	</source>
	<size>
		<width>640</width>
		<height>640</height>
		<depth>3</depth>
	</size>
	<segmented>0</segmented>
	<object>
		<name>Ship</name>
		<pose>Unspecified</pose>
		<truncated>0</truncated>
		<difficult>0</difficult>
		<occluded>0</occluded>
		<bndbox>
			<xmin>28</xmin>
			<xmax>321</xmax>
			<ymin>201</ymin>
			<ymax>438</ymax>
		</bndbox>
	</object>
	<object>
		<name>Ship</name>
		<pose>Unspecified</pose>
		<truncated>0</truncated>
		<difficult>0</difficult>
		<occluded>0</occluded>
		<bndbox>
			<xmin>303</xmin>
			<xmax>602</xmax>
			<ymin>193</ymin>
			<ymax>450</ymax>
		</bndbox>
	</object>
</annotation>
