<annotation>
	<folder></folder>
	<filename>442416_jpg.rf.db2a605e896baf02403558c5d4fae6f8.jpg</filename>
	<path>442416_jpg.rf.db2a605e896baf02403558c5d4fae6f8.jpg</path>
	<source>
		<database>roboflow.com</database>
	</source>
	<size>
		<width>640</width>
		<height>640</height>
		<depth>3</depth>
	</size>
	<segmented>0</segmented>
	<object>
		<name>Ship</name>
		<pose>Unspecified</pose>
		<truncated>0</truncated>
		<difficult>0</difficult>
		<occluded>0</occluded>
		<bndbox>
			<xmin>67</xmin>
			<xmax>547</xmax>
			<ymin>275</ymin>
			<ymax>445</ymax>
		</bndbox>
	</object>
</annotation>
