<annotation>
	<folder></folder>
	<filename>58_jpg.rf.15c22187df5f4c1bae55959a57a6e105.jpg</filename>
	<path>58_jpg.rf.15c22187df5f4c1bae55959a57a6e105.jpg</path>
	<source>
		<database>roboflow.com</database>
	</source>
	<size>
		<width>640</width>
		<height>425</height>
		<depth>3</depth>
	</size>
	<segmented>0</segmented>
	<object>
		<name>Ship</name>
		<pose>Unspecified</pose>
		<truncated>0</truncated>
		<difficult>0</difficult>
		<occluded>0</occluded>
		<bndbox>
			<xmin>371</xmin>
			<xmax>489</xmax>
			<ymin>165</ymin>
			<ymax>369</ymax>
		</bndbox>
		<polygon>
			<x1>487.5</x1>
			<y1>345.625</y1>
			<x2>477.5</x2>
			<y2>338.125</y2>
			<x3>482.5</x3>
			<y3>329.375</y3>
			<x4>471.25</x4>
			<y4>323.125</y4>
			<x5>463.75</x5>
			<y5>281.875</y5>
			<x6>450</x6>
			<y6>245.625</y6>
			<x7>446.875</x7>
			<y7>163.75</y7>
			<x8>440</x8>
			<y8>244.375</y8>
			<x9>430</x9>
			<y9>276.875</y9>
			<x10>428.125</x10>
			<y10>280</y10>
			<x11>422.5</x11>
			<y11>268.125</y11>
			<x12>418.75</x12>
			<y12>246.875</y12>
			<x13>414.375</x13>
			<y13>172.5</y13>
			<x14>408.75</x14>
			<y14>245.625</y14>
			<x15>401.25</x15>
			<y15>265.625</y15>
			<x16>402.5</x16>
			<y16>278.125</y16>
			<x17>396.25</x17>
			<y17>283.125</y17>
			<x18>398.75</x18>
			<y18>286.875</y18>
			<x19>392.5</x19>
			<y19>296.875</y19>
			<x20>390</x20>
			<y20>318.125</y20>
			<x21>379.375</x21>
			<y21>320</y21>
			<x22>371.875</x22>
			<y22>312.5</y22>
			<x23>370</x23>
			<y23>318.125</y23>
			<x24>379.375</x24>
			<y24>362.5</y24>
			<x25>399.375</x25>
			<y25>367.5</y25>
			<x26>465</x26>
			<y26>366.875</y26>
			<x27>480.625</x27>
			<y27>366.25</y27>
			<x28>487.5</x28>
			<y28>345.625</y28>
		</polygon>
	</object>
</annotation>
