<annotation>
	<folder></folder>
	<filename>68_webp.rf.2c74434ffe1c229e66916d48b192dd06.jpg</filename>
	<path>68_webp.rf.2c74434ffe1c229e66916d48b192dd06.jpg</path>
	<source>
		<database>roboflow.com</database>
	</source>
	<size>
		<width>1280</width>
		<height>867</height>
		<depth>3</depth>
	</size>
	<segmented>0</segmented>
	<object>
		<name>Ship</name>
		<pose>Unspecified</pose>
		<truncated>0</truncated>
		<difficult>0</difficult>
		<occluded>0</occluded>
		<bndbox>
			<xmin>124</xmin>
			<xmax>1096</xmax>
			<ymin>364</ymin>
			<ymax>799</ymax>
		</bndbox>
		<polygon>
			<x1>1070</x1>
			<y1>786.25</y1>
			<x2>1072.5</x2>
			<y2>706.25</y2>
			<x3>1095</x3>
			<y3>656.25</y3>
			<x4>1088.75</x4>
			<y4>645</y4>
			<x5>1078.75</x5>
			<y5>650</y5>
			<x6>1051.25</x6>
			<y6>652.5</y6>
			<x7>1047.5</x7>
			<y7>648.75</y7>
			<x8>1047.5</x8>
			<y8>626.25</y8>
			<x9>1038.75</x9>
			<y9>615</y9>
			<x10>1028.75</x10>
			<y10>615</y10>
			<x11>1020</x11>
			<y11>626.25</y11>
			<x12>1022.5</x12>
			<y12>636.25</y12>
			<x13>1027.5</x13>
			<y13>638.75</y13>
			<x14>1026.25</x14>
			<y14>650</y14>
			<x15>978.75</x15>
			<y15>655</y15>
			<x16>972.5</x16>
			<y16>648.75</y16>
			<x17>972.5</x17>
			<y17>528.75</y17>
			<x18>980</x18>
			<y18>518.75</y18>
			<x19>972.5</x19>
			<y19>511.25</y19>
			<x20>987.5</x20>
			<y20>498.75</y20>
			<x21>973.75</x21>
			<y21>495</y21>
			<x22>966.25</x22>
			<y22>477.5</y22>
			<x23>962.5</x23>
			<y23>493.75</y23>
			<x24>942.5</x24>
			<y24>501.25</y24>
			<x25>960</x25>
			<y25>508.75</y25>
			<x26>960</x26>
			<y26>513.75</y26>
			<x27>952.5</x27>
			<y27>518.75</y27>
			<x28>962.5</x28>
			<y28>528.75</y28>
			<x29>962.5</x29>
			<y29>641.25</y29>
			<x30>951.25</x30>
			<y30>652.5</y30>
			<x31>941.25</x31>
			<y31>652.5</y31>
			<x32>937.5</x32>
			<y32>648.75</y32>
			<x33>935</x33>
			<y33>621.25</y33>
			<x34>921.25</x34>
			<y34>615</y34>
			<x35>915</x35>
			<y35>623.75</y35>
			<x36>920</x36>
			<y36>636.25</y36>
			<x37>917.5</x37>
			<y37>651.25</y37>
			<x38>911.25</x38>
			<y38>650</y38>
			<x39>886.25</x39>
			<y39>660</y39>
			<x40>878.75</x40>
			<y40>672.5</y40>
			<x41>681.25</x41>
			<y41>672.5</y41>
			<x42>670</x42>
			<y42>668.75</y42>
			<x43>667.5</x43>
			<y43>626.25</y43>
			<x44>653.75</x44>
			<y44>617.5</y44>
			<x45>598.75</x45>
			<y45>622.5</y45>
			<x46>503.75</x46>
			<y46>622.5</y46>
			<x47>488.75</x47>
			<y47>630</y47>
			<x48>481.25</x48>
			<y48>620</y48>
			<x49>476.25</x49>
			<y49>620</y49>
			<x50>467.5</x50>
			<y50>651.25</y50>
			<x51>467.5</x51>
			<y51>666.25</y51>
			<x52>463.75</x52>
			<y52>670</y52>
			<x53>441.25</x53>
			<y53>670</y53>
			<x54>437.5</x54>
			<y54>653.75</y54>
			<x55>441.25</x55>
			<y55>650</y55>
			<x56>458.75</x56>
			<y56>650</y56>
			<x57>465</x57>
			<y57>643.75</y57>
			<x58>465</x58>
			<y58>623.75</y58>
			<x59>458.75</x59>
			<y59>620</y59>
			<x60>438.75</x60>
			<y60>620</y60>
			<x61>427.5</x61>
			<y61>611.25</y61>
			<x62>430</x62>
			<y62>591.25</y62>
			<x63>422.5</x63>
			<y63>583.75</y63>
			<x64>422.5</x64>
			<y64>578.75</y64>
			<x65>435</x65>
			<y65>563.75</y65>
			<x66>435</x66>
			<y66>551.25</y66>
			<x67>431.25</x67>
			<y67>547.5</y67>
			<x68>420</x68>
			<y68>551.25</y68>
			<x69>420</x69>
			<y69>571.25</y69>
			<x70>408.75</x70>
			<y70>582.5</y70>
			<x71>393.75</x71>
			<y71>580</y71>
			<x72>381.25</x72>
			<y72>587.5</y72>
			<x73>363.75</x73>
			<y73>587.5</y73>
			<x74>360</x74>
			<y74>583.75</y74>
			<x75>360</x75>
			<y75>563.75</y75>
			<x76>351.25</x76>
			<y76>562.5</y76>
			<x77>347.5</x77>
			<y77>566.25</y77>
			<x78>350</x78>
			<y78>586.25</y78>
			<x79>341.25</x79>
			<y79>587.5</y79>
			<x80>337.5</x80>
			<y80>583.75</y80>
			<x81>340</x81>
			<y81>533.75</y81>
			<x82>351.25</x82>
			<y82>527.5</y82>
			<x83>356.25</x83>
			<y83>535</y83>
			<x84>360</x84>
			<y84>526.25</y84>
			<x85>357.5</x85>
			<y85>481.25</y85>
			<x86>352.5</x86>
			<y86>483.75</y86>
			<x87>352.5</x87>
			<y87>508.75</y87>
			<x88>346.25</x88>
			<y88>515</y88>
			<x89>326.25</x89>
			<y89>512.5</y89>
			<x90>320</x90>
			<y90>506.25</y90>
			<x91>312.5</x91>
			<y91>468.75</y91>
			<x92>312.5</x92>
			<y92>443.75</y92>
			<x93>330</x93>
			<y93>431.25</y93>
			<x94>312.5</x94>
			<y94>421.25</y94>
			<x95>310</x95>
			<y95>401.25</y95>
			<x96>320</x96>
			<y96>391.25</y96>
			<x97>320</x97>
			<y97>383.75</y97>
			<x98>310</x98>
			<y98>378.75</y98>
			<x99>307.5</x99>
			<y99>366.25</y99>
			<x100>301.25</x100>
			<y100>362.5</y100>
			<x101>300</x101>
			<y101>378.75</y101>
			<x102>287.5</x102>
			<y102>386.25</y102>
			<x103>300</x103>
			<y103>398.75</y103>
			<x104>302.5</x104>
			<y104>416.25</y104>
			<x105>298.75</x105>
			<y105>422.5</y105>
			<x106>283.75</x106>
			<y106>422.5</y106>
			<x107>280</x107>
			<y107>428.75</y107>
			<x108>283.75</x108>
			<y108>435</y108>
			<x109>302.5</x109>
			<y109>443.75</y109>
			<x110>305</x110>
			<y110>496.25</y110>
			<x111>302.5</x111>
			<y111>503.75</y111>
			<x112>296.25</x112>
			<y112>510</y112>
			<x113>293.75</x113>
			<y113>507.5</y113>
			<x114>285</x114>
			<y114>518.75</y114>
			<x115>287.5</x115>
			<y115>541.25</y115>
			<x116>285</x116>
			<y116>556.25</y116>
			<x117>277.5</x117>
			<y117>563.75</y117>
			<x118>280</x118>
			<y118>581.25</y118>
			<x119>268.75</x119>
			<y119>585</y119>
			<x120>228.75</x120>
			<y120>585</y120>
			<x121>221.25</x121>
			<y121>575</y121>
			<x122>208.75</x122>
			<y122>590</y122>
			<x123>181.25</x123>
			<y123>597.5</y123>
			<x124>140</x124>
			<y124>621.25</y124>
			<x125>137.5</x125>
			<y125>633.75</y125>
			<x126>125</x126>
			<y126>651.25</y126>
			<x127>122.5</x127>
			<y127>713.75</y127>
			<x128>127.5</x128>
			<y128>736.25</y128>
			<x129>141.25</x129>
			<y129>755</y129>
			<x130>211.25</x130>
			<y130>797.5</y130>
			<x131>490</x131>
			<y131>796.25</y131>
			<x132>1063.75</x132>
			<y132>792.5</y132>
			<x133>1070</x133>
			<y133>786.25</y133>
		</polygon>
	</object>
</annotation>
