<annotation>
	<folder></folder>
	<filename>733724_jpg.rf.02a78d4b1e08554a35aa8ec6d5e55f01.jpg</filename>
	<path>733724_jpg.rf.02a78d4b1e08554a35aa8ec6d5e55f01.jpg</path>
	<source>
		<database>roboflow.com</database>
	</source>
	<size>
		<width>640</width>
		<height>640</height>
		<depth>3</depth>
	</size>
	<segmented>0</segmented>
	<object>
		<name>Ship</name>
		<pose>Unspecified</pose>
		<truncated>0</truncated>
		<difficult>0</difficult>
		<occluded>0</occluded>
		<bndbox>
			<xmin>201</xmin>
			<xmax>611</xmax>
			<ymin>208</ymin>
			<ymax>416</ymax>
		</bndbox>
	</object>
</annotation>
