<annotation>
	<folder></folder>
	<filename>images-80_jpg.rf.09ba7386fd04947179302d41f61e44d7.jpg</filename>
	<path>images-80_jpg.rf.09ba7386fd04947179302d41f61e44d7.jpg</path>
	<source>
		<database>roboflow.com</database>
	</source>
	<size>
		<width>416</width>
		<height>416</height>
		<depth>3</depth>
	</size>
	<segmented>0</segmented>
	<object>
		<name>Ship</name>
		<pose>Unspecified</pose>
		<truncated>0</truncated>
		<difficult>0</difficult>
		<occluded>0</occluded>
		<bndbox>
			<xmin>1</xmin>
			<xmax>142</xmax>
			<ymin>85</ymin>
			<ymax>307</ymax>
		</bndbox>
	</object>
	<object>
		<name>Ship</name>
		<pose>Unspecified</pose>
		<truncated>0</truncated>
		<difficult>0</difficult>
		<occluded>0</occluded>
		<bndbox>
			<xmin>133</xmin>
			<xmax>416</xmax>
			<ymin>32</ymin>
			<ymax>416</ymax>
		</bndbox>
	</object>
</annotation>
